charstyle/__init__.py
charstyle/__main__.py
charstyle/align.py
charstyle/charstyle.py
charstyle/icons.py
charstyle/pattern_style.py
charstyle/styles.py
charstyle/tables.py
charstyle/cli/__init__.py
charstyle/cli/icons_display.py
charstyle/cli/styles_display.py
charstyle/cli/tables_display.py
charstyle-0.4.0.dist-info/METADATA
charstyle-0.4.0.dist-info/WHEEL
charstyle-0.4.0.dist-info/licenses/LICENSE
charstyle-0.4.0.dist-info/RECORD
