Metadata-Version: 2.4
Name: charstyle
Version: 0.4.0
Summary: A library for styling terminal text with ANSI escape sequences
Project-URL: Homepage, https://github.com/joaompinto/charstyle
Project-URL: Repository, https://github.com/joaompinto/charstyle
Project-URL: Issues, https://github.com/joaompinto/charstyle/issues
Author-email: João Pinto <lamego.pinto@gmail.com>
License: MIT
License-File: LICENSE
Requires-Python: >=3.11
